pepino/__init__.py
pepino/definitions.py
pepino/enums.py
pepino/exceptions.py
pepino/hooks.py
pepino/logging.py
pepino/registry.py
pepino/results.py
pepino/steps.py
pepino/data/__init__.py
pepino/data/doc.py
pepino/data/table.py
pepino/gherkin/__init__.py
pepino/gherkin/definitions.py
pepino/gherkin/location.py
pepino/gherkin/data/__init__.py
pepino/gherkin/data/doc.py
pepino/gherkin/data/table.py
pepino/plugin/__init__.py
pepino/plugin/main.py
pepino/plugin/pytest.py
pepino_bdd-1.0.0.dist-info/LICENSE
pepino_bdd-1.0.0.dist-info/METADATA
pepino_bdd-1.0.0.dist-info/WHEEL
pepino_bdd-1.0.0.dist-info/entry_points.txt
pepino_bdd-1.0.0.dist-info/top_level.txt
pepino_bdd-1.0.0.dist-info/RECORD
