Metadata-Version: 2.1
Name: pepino-bdd
Version: 1.0.0
Summary: Pepino BDD
Home-page: https://github.com/patrickguk/pepino
Author: Patrick Gallagher
License: GPL2.0
Keywords: Cucumber,Gherkin,BDD
Platform: UNKNOWN
Classifier: Development Status :: 3 - Alpha
Classifier: Intended Audience :: Developers
Classifier: Topic :: Software Development :: Testing :: BDD
Classifier: License :: OSI Approved :: GNU General Public License v2 (GPLv2)
Classifier: Programming Language :: Python :: 3
Classifier: Programming Language :: Python :: 3.7
Classifier: Programming Language :: Python :: 3.8
Classifier: Programming Language :: Python :: 3.9
License-File: LICENSE
Requires-Dist: gherkin-official
Requires-Dist: termcolor
